{
  "tasks": [
    {
      "id": "258e7e50-5bb2-4e29-81ba-91a04d9cd655",
      "title": "Покормить",
      "description": "Положить сухой корм и налить свежую воду для кота"
    },
    {
      "id": "15c67de9-6e85-4a1d-8484-40f0d11e37d6",
      "title": "Выгул",
      "description": "Прогулка с собакой в парке на 30 минут"
    },
    {
      "id": "1a52093a-b925-406a-a187-93c4440e4a2b",
      "title": "Чистка",
      "description": "Очистить аквариум и заменить воду для рыбок"
    },
    {
      "id": "dda45233-4ad2-4083-a666-d2359721fe61",
      "title": "Купание",
      "description": "Аккуратно помыть хомяка специальным шампунем"
    },
    {
      "id": "3b429d46-26e6-4efd-a0c9-e517e262819e",
      "title": "Проверка",
      "description": "Убедиться, что клетка чистая и кормушка полная"
    },
    {
      "id": "8d839f57-b069-4298-8a8a-bf8ce6ea8ce3",
      "title": "Покупка",
      "description": "Купить свежие овощи и специальный корм для кролика"
    },
    {
      "id": "6b7485f1-7d7f-4d71-a9ff-817389e73f22",
      "title": "Чистка",
      "description": "Очистить и продезинфицировать кошачий лоток"
    },
    {
      "id": "31160ad6-b25f-49c1-ad45-4453479df93a",
      "title": "Обработка",
      "description": "Расчесать шерсть собаки и проверить на наличие паразитов"
    },
    {
      "id": "cbb78b45-de76-4473-9aea-ff34b5e49db7",
      "title": "Обновление",
      "description": "Заменить воду в террариуме и проверить фильтр"
    },
    {
      "id": "18c6c1b1-ad06-40c9-9a09-1f5a44c39747",
      "title": "Игры",
      "description": "Провести время, играя с попугаем и обучая его новым словам"
    },
    {
      "id": "38470a5d-a4b7-47c2-97bb-327f09d320d6",
      "title": "Проверка",
      "description": "Осмотреть когти кота и подстричь при необходимости"
    },
    {
      "id": "55affcf7-f338-4971-b4d0-ffd6fc276b8c",
      "title": "Чистка",
      "description": "Почистить уши собаки специальным средством"
    },
    {
      "id": "e5494510-e00b-4d8c-9439-9bd6dcdd9ea9",
      "title": "Проверка",
      "description": "Заменить песок для купания хомяка"
    },
    {
      "id": "f123cac3-203f-48e0-808d-0a177b59e3d7",
      "title": "Смена",
      "description": "Заменить подстилку в клетке кролика"
    },
    {
      "id": "f9cc3dfc-10a9-4217-8d22-f82697a431f9",
      "title": "Подготовка",
      "description": "Приготовить свежие фрукты и зерновую смесь для попугая"
    },
    {
      "id": "92ac7a4f-123a-44c4-b38c-610213971758",
      "title": "Покормить",
      "description": "Положить сухой корм и налить свежую воду для кота"
    },
    {
      "id": "9fc0029e-2134-49c3-8efe-7ab4378ce82c",
      "title": "Выгул",
      "description": "Прогулка с собакой в парке на 30 минут"
    },
    {
      "id": "15f42d9e-210d-40f3-8d4e-0c0ef15a0940",
      "title": "Чистка",
      "description": "Очистить аквариум и заменить воду для рыбок"
    },
    {
      "id": "bfb9cfa7-a10d-45ee-9ac3-d38b3d5761fa",
      "title": "Купание",
      "description": "Аккуратно помыть хомяка специальным шампунем"
    },
    {
      "id": "a24875ef-964c-4eb4-9061-b770e114680a",
      "title": "Проверка",
      "description": "Убедиться, что клетка чистая и кормушка полная"
    },
    {
      "id": "b08a8727-d66d-4b65-bf29-e45ae3c910cd",
      "title": "Покупка",
      "description": "Купить свежие овощи и специальный корм для кролика"
    },
    {
      "id": "13098724-728d-44f8-9824-10a3a73c55f1",
      "title": "Чистка",
      "description": "Очистить и продезинфицировать кошачий лоток"
    },
    {
      "id": "448dab86-13d5-41ad-ab58-e82e855ed9a7",
      "title": "Обработка",
      "description": "Расчесать шерсть собаки и проверить на наличие паразитов"
    },
    {
      "id": "85dffb93-6f31-41ba-80c6-7225fe89b6a1",
      "title": "Обновление",
      "description": "Заменить воду в террариуме и проверить фильтр"
    },
    {
      "id": "1fd15766-96f8-4cdc-9f82-e2146df96e08",
      "title": "Игры",
      "description": "Провести время, играя с попугаем и обучая его новым словам"
    },
    {
      "id": "8b988fb2-4253-443d-b8b3-84530a6eb9a1",
      "title": "Проверка",
      "description": "Осмотреть когти кота и подстричь при необходимости"
    },
    {
      "id": "384900f7-477c-4a24-aad3-28524766dc5c",
      "title": "Чистка",
      "description": "Почистить уши собаки специальным средством"
    },
    {
      "id": "134470be-7fb0-4c1b-8e6c-3e43699778e0",
      "title": "Проверка",
      "description": "Заменить песок для купания хомяка"
    },
    {
      "id": "b372f159-6052-408e-b84e-7edbfc38f675",
      "title": "Смена",
      "description": "Заменить подстилку в клетке кролика"
    },
    {
      "id": "94a10823-c4c4-423d-a1e8-5d7d52bb4a63",
      "title": "Подготовка",
      "description": "Приготовить свежие фрукты и зерновую смесь для попугая"
    },
    {
      "id": "c4b32e9c-182e-4089-8bdc-838f965807fa",
      "title": "Покормить",
      "description": "Положить сухой корм и налить свежую воду для кота"
    },
    {
      "id": "118276ca-b20b-4379-a9cf-c5935321184f",
      "title": "Выгул",
      "description": "Прогулка с собакой в парке на 30 минут"
    },
    {
      "id": "489ab6bb-a692-46f6-a650-ea0de5c8ba03",
      "title": "Чистка",
      "description": "Очистить аквариум и заменить воду для рыбок"
    },
    {
      "id": "5984c039-cd93-45a2-a834-69a3b88f2d6f",
      "title": "Купание",
      "description": "Аккуратно помыть хомяка специальным шампунем"
    },
    {
      "id": "1ad9bc75-25bd-4e6b-8d06-638b3f098cd8",
      "title": "Проверка",
      "description": "Убедиться, что клетка чистая и кормушка полная"
    },
    {
      "id": "6e60c955-7347-4895-88f1-425a03b7cb2b",
      "title": "Покупка",
      "description": "Купить свежие овощи и специальный корм для кролика"
    },
    {
      "id": "fbc61fed-77b4-4281-82bb-c0c18ca30f78",
      "title": "Чистка",
      "description": "Очистить и продезинфицировать кошачий лоток"
    },
    {
      "id": "6bf7933d-9ec4-4bab-b86b-2dd28debc91c",
      "title": "Обработка",
      "description": "Расчесать шерсть собаки и проверить на наличие паразитов"
    },
    {
      "id": "6609a8b1-6675-4a27-88ff-0d2a9449ba47",
      "title": "Обновление",
      "description": "Заменить воду в террариуме и проверить фильтр"
    },
    {
      "id": "97d4ed7b-b0d1-4e18-8743-25e1f9ffa81e",
      "title": "Игры",
      "description": "Провести время, играя с попугаем и обучая его новым словам"
    },
    {
      "id": "356d603b-f9b0-4736-9a18-d95e8decadc1",
      "title": "Проверка",
      "description": "Осмотреть когти кота и подстричь при необходимости"
    },
    {
      "id": "b5d00b25-3502-4038-88bc-0e2a9f4c8d7f",
      "title": "Чистка",
      "description": "Почистить уши собаки специальным средством"
    },
    {
      "id": "46bd6d64-9572-42f6-8ef8-3881b3cf712e",
      "title": "Проверка",
      "description": "Заменить песок для купания хомяка"
    },
    {
      "id": "56db71ff-eab0-410f-be42-ae1aede68f23",
      "title": "Смена",
      "description": "Заменить подстилку в клетке кролика"
    },
    {
      "id": "84dbd6d4-f68c-444a-8a08-a13f271faeb8",
      "title": "Подготовка",
      "description": "Приготовить свежие фрукты и зерновую смесь для попугая"
    },
    {
      "id": "7b07580b-295b-4503-a15e-385e93cd6239",
      "title": "Покормить",
      "description": "Положить сухой корм и налить свежую воду для кота"
    },
    {
      "id": "8550fb0c-9f25-4b1f-87a9-c2fafd3b494c",
      "title": "Выгул",
      "description": "Прогулка с собакой в парке на 30 минут"
    },
    {
      "id": "359e9606-f693-4ea3-9014-0c8b93462342",
      "title": "Чистка",
      "description": "Очистить аквариум и заменить воду для рыбок"
    },
    {
      "id": "0c12f4da-5f2b-4c62-aab4-c53b0a83a4fa",
      "title": "Купание",
      "description": "Аккуратно помыть хомяка специальным шампунем"
    },
    {
      "id": "0d0e1c0b-e7df-4380-b1be-33b08be70aba",
      "title": "Проверка",
      "description": "Убедиться, что клетка чистая и кормушка полная"
    }
  ]
}
